odoo/addons/delivery_dachser/README.rst
odoo/addons/delivery_dachser/__init__.py
odoo/addons/delivery_dachser/__manifest__.py
odoo/addons/delivery_dachser/data/product_packaging_data.xml
odoo/addons/delivery_dachser/doc/DACHSER API Codelist (V4.0.2 ).xlsx
odoo/addons/delivery_dachser/i18n/delivery_dachser.pot
odoo/addons/delivery_dachser/i18n/es.po
odoo/addons/delivery_dachser/i18n/it.po
odoo/addons/delivery_dachser/models/__init__.py
odoo/addons/delivery_dachser/models/dachser_master_data.py
odoo/addons/delivery_dachser/models/dachser_request.py
odoo/addons/delivery_dachser/models/delivery_carrier.py
odoo/addons/delivery_dachser/models/stock_package_type.py
odoo/addons/delivery_dachser/readme/CONFIGURE.md
odoo/addons/delivery_dachser/readme/CONTRIBUTORS.md
odoo/addons/delivery_dachser/readme/DESCRIPTION.md
odoo/addons/delivery_dachser/readme/INSTALL.md
odoo/addons/delivery_dachser/readme/USAGE.md
odoo/addons/delivery_dachser/static/description/icon.png
odoo/addons/delivery_dachser/static/description/index.html
odoo/addons/delivery_dachser/tests/__init__.py
odoo/addons/delivery_dachser/tests/test_delivery_dachser.py
odoo/addons/delivery_dachser/views/delivery_carrier_views.xml
odoo_addon_delivery_dachser-18.0.1.0.0.2.dist-info/METADATA
odoo_addon_delivery_dachser-18.0.1.0.0.2.dist-info/WHEEL
odoo_addon_delivery_dachser-18.0.1.0.0.2.dist-info/top_level.txt
odoo_addon_delivery_dachser-18.0.1.0.0.2.dist-info/RECORD
